LICENSE.md
README.md
setup.py
ymbotpy/__init__.py
ymbotpy/api.py
ymbotpy/audio.py
ymbotpy/channel.py
ymbotpy/client.py
ymbotpy/connection.py
ymbotpy/errors.py
ymbotpy/flags.py
ymbotpy/forum.py
ymbotpy/gateway.py
ymbotpy/guild.py
ymbotpy/http.py
ymbotpy/interaction.py
ymbotpy/logging.py
ymbotpy/manage.py
ymbotpy/message.py
ymbotpy/reaction.py
ymbotpy/robot.py
ymbotpy/user.py
ymbotpy.egg-info/PKG-INFO
ymbotpy.egg-info/SOURCES.txt
ymbotpy.egg-info/dependency_links.txt
ymbotpy.egg-info/requires.txt
ymbotpy.egg-info/top_level.txt
ymbotpy/ext/__init__.py
ymbotpy/ext/command_util.py
ymbotpy/ext/channel_jump/__init__.py
ymbotpy/ext/cog_apscheduler/__init__.py
ymbotpy/ext/cog_yaml/__init__.py
ymbotpy/ext/convert_color/__init__.py
ymbotpy/types/__init__.py
ymbotpy/types/announce.py
ymbotpy/types/audio.py
ymbotpy/types/channel.py
ymbotpy/types/emoji.py
ymbotpy/types/forum.py
ymbotpy/types/gateway.py
ymbotpy/types/guild.py
ymbotpy/types/inline.py
ymbotpy/types/interaction.py
ymbotpy/types/message.py
ymbotpy/types/permission.py
ymbotpy/types/pins_message.py
ymbotpy/types/reaction.py
ymbotpy/types/rich_text.py
ymbotpy/types/robot.py
ymbotpy/types/schedule.py
ymbotpy/types/session.py
ymbotpy/types/user.py