Metadata-Version: 2.1
Name: ymbotpy
Version: 1.1.0.dev0
Summary: QQ robot webhook server using Python 3
Home-page: https://github.com/HG-ha/ym-qq-botpy
Author: yiming
Author-email: 1790233968@qq.com
License: YiMing
Classifier: Development Status :: 4 - Beta
Classifier: Intended Audience :: Developers
Classifier: Topic :: Software Development
Classifier: License :: OSI Approved :: MIT License
Classifier: Programming Language :: Python :: 3.7
License-File: LICENSE.md
Requires-Dist: aiohttp<4,>=3.7.4
Requires-Dist: PyYAML
Requires-Dist: APScheduler
Requires-Dist: cryptography>=40.0.0
Requires-Dist: fastapi>=0.115.0
Requires-Dist: multidict
Requires-Dist: uvicorn
